{"1": {"Task": 2, "D": 0.25, "P": 4, "F": 3, "IR": false, "IH": false, "S": 0, "IM": false, "TK": 5, "W": 1, "COM": 1, "NM": 9}, "0": {"QA": [true, "male", "24", "RO", "CS", "2", "no", "5", "6", "4", "MD", "OLD", "RT", "RH", "RF", "C", "4"], "T0": 4}, "3": {"Task": 1, "D": 0.5, "P": 7, "F": 0, "IR": false, "IH": false, "S": 0, "IM": false, "TK": 5, "W": 1, "COM": 1, "NM": 9}, "2": {"Task": 3, "D": 0.25, "P": 7, "F": 0, "IR": false, "IH": false, "S": 0, "IM": false, "TK": 5, "W": 1, "COM": 1, "NM": 9}}