{"24": {"task": 1, "type": "MainPage", "dateString": "2019-04-26T07:51:25.798Z", "name": "HeadSuccessful"}, "25": {"task": 1, "name": "VerifyResult", "result_success": true, "dateString": "2019-04-26T07:51:44.215Z", "answers": {"PLANT": true}, "has_intervene": false, "type": "MainPage"}, "26": {"type": "MainPage", "dateString": "2019-04-26T07:51:49.281Z", "name": "SelectNewTask"}, "27": {"type": "MainPage", "dateString": "2019-04-26T07:51:53.082Z", "name": "SelectNewTask"}, "20": {"type": "MainPage", "dateString": "2019-04-26T07:50:34.461Z", "name": "SelectNewTask"}, "21": {"type": "MainPage", "dateString": "2019-04-26T07:50:36.765Z", "name": "SelectNewTask"}, "22": {"task": 1, "type": "MainPage", "dateString": "2019-04-26T07:50:38.463Z", "name": "TaskStarted"}, "23": {"task": 1, "type": "MainPage", "dateString": "2019-04-26T07:51:02.133Z", "name": "MoveSuccesfull"}, "28": {"task": 2, "type": "MainPage", "dateString": "2019-04-26T07:52:04.020Z", "name": "TaskStarted"}, "29": {"task": 2, "type": "MainPage", "dateString": "2019-04-26T07:52:25.420Z", "name": "MoveSuccesfull"}, "40": {"type": "ThankYouPage", "dateString": "2019-04-26T07:53:31.679Z", "value": 2, "name": "ConversationFinished"}, "1": {"type": "LoginPage", "dateString": "2019-04-26T07:37:24.153Z", "name": "NextButtonPressed"}, "0": {"type": "LoginPage", "dateString": "2019-04-26T07:37:01.267Z", "name": "PageOpened"}, "3": {"type": "TiagoInfoPage", "dateString": "2019-04-26T07:38:09.304Z", "name": "PageOpened"}, "2": {"type": "ExperimentInfoPage", "dateString": "2019-04-26T07:37:24.209Z", "name": "PageOpened"}, "5": {"task": "2", "type": "TaskInfoPage", "dateString": "2019-04-26T07:39:33.091Z", "value": 0.75, "name": "TaskInfoSubmmitDificulty"}, "4": {"type": "TaskInfoPage", "dateString": "2019-04-26T07:38:21.718Z", "name": "PageOpened"}, "7": {"task": "3", "type": "TaskInfoPage", "dateString": "2019-04-26T07:39:58.251Z", "value": 0.5, "name": "TaskInfoSubmmitDificulty"}, "6": {"type": "TaskInfoPage", "dateString": "2019-04-26T07:39:33.091Z", "name": "NextButtonPressed"}, "9": {"task": "1", "type": "TaskInfoPage", "dateString": "2019-04-26T07:40:13.335Z", "value": 0.5, "name": "TaskInfoSubmmitDificulty"}, "8": {"type": "TaskInfoPage", "dateString": "2019-04-26T07:39:58.251Z", "name": "NextButtonPressed"}, "39": {"type": "MainPage", "dateString": "2019-04-26T07:53:31.626Z", "name": "Experiemntfinished"}, "38": {"task": 2, "name": "VerifyResult", "result_success": false, "dateString": "2019-04-26T07:53:19.517Z", "answers": {"TV": false, "CHAIR": false, "LIVING ROOM": false, "COFFEE TABLE": false, "COUCH": false}, "has_intervene": false, "type": "MainPage"}, "11": {"type": "PreQuestionsPage", "dateString": "2019-04-26T07:40:45.755Z", "name": "PageOpened"}, "10": {"type": "TaskInfoPage", "dateString": "2019-04-26T07:40:13.335Z", "name": "NextButtonPressed"}, "13": {"type": "MainPage", "dateString": "2019-04-26T07:47:57.706Z", "name": "SelectNewTask"}, "12": {"type": "MainPage", "dateString": "2019-04-26T07:43:34.793Z", "name": "PageOpened"}, "15": {"task": 3, "type": "MainPage", "dateString": "2019-04-26T07:48:30.417Z", "name": "MoveSuccesfull"}, "14": {"task": 3, "type": "MainPage", "dateString": "2019-04-26T07:48:02.469Z", "name": "TaskStarted"}, "17": {"task": 3, "type": "MainPage", "dateString": "2019-04-26T07:49:30.293Z", "name": "MoveSuccesfull"}, "16": {"task": 3, "type": "MainPage", "dateString": "2019-04-26T07:49:00.033Z", "name": "HeadSuccessful"}, "19": {"task": 3, "name": "VerifyResult", "result_success": true, "dateString": "2019-04-26T07:50:20.655Z", "answers": {"CHAIR": true, "XBOX": false, "COFFEE TABLE": true, "BED": true, "COUCH": true}, "has_intervene": false, "type": "MainPage"}, "18": {"task": 3, "type": "MainPage", "dateString": "2019-04-26T07:49:58.544Z", "name": "HeadSuccessful"}, "31": {"task": 2, "name": "HeadMovedLR", "dateString": "2019-04-26T07:52:47.453Z", "heady": 0, "headx": 0, "type": "MainPage"}, "30": {"task": 2, "type": "MainPage", "dateString": "2019-04-26T07:52:45.492Z", "name": "HeadIntervention"}, "37": {"task": 2, "type": "MainPage", "dateString": "2019-04-26T07:53:00.861Z", "name": "HeadSuccessful"}, "36": {"task": 2, "type": "MainPage", "dateString": "2019-04-26T07:53:00.861Z", "name": "HeadFinishedIntervention"}, "35": {"task": 2, "name": "HeadMovedUD", "dateString": "2019-04-26T07:52:59.464Z", "heady": 0, "headx": 0, "type": "MainPage"}, "34": {"task": 2, "name": "HeadMovedUD", "dateString": "2019-04-26T07:52:56.565Z", "heady": -18, "headx": 0, "type": "MainPage"}, "33": {"task": 2, "name": "HeadMovedUD", "dateString": "2019-04-26T07:52:53.060Z", "heady": 0, "headx": 0, "type": "MainPage"}, "32": {"task": 2, "name": "HeadMovedUD", "dateString": "2019-04-26T07:52:50.623Z", "heady": 17, "headx": 0, "type": "MainPage"}}