{"24": {"task": 2, "name": "HeadMovedLR", "dateString": "2019-04-18T17:36:58.923Z", "heady": -40, "headx": -107, "type": "MainPage"}, "25": {"task": 2, "name": "HeadMovedLR", "dateString": "2019-04-18T17:37:01.106Z", "heady": -40, "headx": -77, "type": "MainPage"}, "26": {"task": 2, "name": "HeadMovedLR", "dateString": "2019-04-18T17:37:03.487Z", "heady": -40, "headx": 85, "type": "MainPage"}, "27": {"task": 2, "name": "HeadMovedLR", "dateString": "2019-04-18T17:37:08.554Z", "heady": -40, "headx": -117, "type": "MainPage"}, "20": {"task": 2, "type": "MainPage", "dateString": "2019-04-18T17:36:15.420Z", "name": "TaskStarted"}, "21": {"task": 2, "type": "MainPage", "dateString": "2019-04-18T17:36:38.591Z", "name": "MoveSuccesfull"}, "22": {"task": 2, "type": "MainPage", "dateString": "2019-04-18T17:36:41.855Z", "name": "HeadIntervention"}, "23": {"task": 2, "name": "HeadMovedUD", "dateString": "2019-04-18T17:36:55.304Z", "heady": -40, "headx": 0, "type": "MainPage"}, "28": {"task": 2, "name": "HeadMovedUD", "dateString": "2019-04-18T17:37:12.756Z", "heady": -20, "headx": -117, "type": "MainPage"}, "29": {"task": 2, "name": "HeadMovedUD", "dateString": "2019-04-18T17:37:15.787Z", "heady": 4, "headx": -117, "type": "MainPage"}, "40": {"type": "ThankYouPage", "dateString": "2019-04-18T17:40:21.873Z", "value": 2, "name": "ConversationFinished"}, "1": {"type": "LoginPage", "dateString": "2019-04-18T17:32:15.415Z", "name": "NextButtonPressed"}, "0": {"type": "LoginPage", "dateString": "2019-04-18T17:32:10.651Z", "name": "PageOpened"}, "3": {"type": "TiagoInfoPage", "dateString": "2019-04-18T17:32:16.752Z", "name": "PageOpened"}, "2": {"type": "ExperimentInfoPage", "dateString": "2019-04-18T17:32:15.479Z", "name": "PageOpened"}, "5": {"task": "1", "type": "TaskInfoPage", "dateString": "2019-04-18T17:32:19.595Z", "value": 0.5, "name": "TaskInfoSubmmitDificulty"}, "4": {"type": "TaskInfoPage", "dateString": "2019-04-18T17:32:18.573Z", "name": "PageOpened"}, "7": {"task": "2", "type": "TaskInfoPage", "dateString": "2019-04-18T17:32:20.150Z", "value": 0.5, "name": "TaskInfoSubmmitDificulty"}, "6": {"type": "TaskInfoPage", "dateString": "2019-04-18T17:32:19.596Z", "name": "NextButtonPressed"}, "9": {"task": "3", "type": "TaskInfoPage", "dateString": "2019-04-18T17:32:20.660Z", "value": 0.5, "name": "TaskInfoSubmmitDificulty"}, "8": {"type": "TaskInfoPage", "dateString": "2019-04-18T17:32:20.150Z", "name": "NextButtonPressed"}, "39": {"type": "MainPage", "dateString": "2019-04-18T17:40:21.775Z", "name": "Experiemntfinished"}, "38": {"type": "MainPage", "dateString": "2019-04-18T17:38:11.556Z", "name": "SelectNewTask"}, "11": {"type": "PreQuestionsPage", "dateString": "2019-04-18T17:32:22.975Z", "name": "PageOpened"}, "10": {"type": "TaskInfoPage", "dateString": "2019-04-18T17:32:20.660Z", "name": "NextButtonPressed"}, "13": {"type": "MainPage", "dateString": "2019-04-18T17:34:57.222Z", "name": "SelectNewTask"}, "12": {"type": "MainPage", "dateString": "2019-04-18T17:34:34.732Z", "name": "PageOpened"}, "15": {"task": 1, "type": "MainPage", "dateString": "2019-04-18T17:35:20.433Z", "name": "MoveSuccesfull"}, "14": {"task": 1, "type": "MainPage", "dateString": "2019-04-18T17:34:58.740Z", "name": "TaskStarted"}, "17": {"task": 1, "name": "VerifyResult", "result_success": false, "dateString": "2019-04-18T17:36:00.754Z", "answers": {"PLANT": false}, "has_intervene": false, "type": "MainPage"}, "16": {"task": 1, "type": "MainPage", "dateString": "2019-04-18T17:35:42.909Z", "name": "HeadSuccessful"}, "19": {"type": "MainPage", "dateString": "2019-04-18T17:36:13.711Z", "name": "SelectNewTask"}, "18": {"type": "MainPage", "dateString": "2019-04-18T17:36:11.467Z", "name": "SelectNewTask"}, "31": {"task": 2, "name": "HeadMovedUD", "dateString": "2019-04-18T17:37:19.662Z", "heady": -9, "headx": -117, "type": "MainPage"}, "30": {"task": 2, "name": "HeadMovedUD", "dateString": "2019-04-18T17:37:18.007Z", "heady": 49, "headx": -117, "type": "MainPage"}, "37": {"task": 2, "name": "VerifyResult", "result_success": false, "dateString": "2019-04-18T17:37:58.857Z", "answers": {"TV": true, "CHAIR": false, "LIVING ROOM": false, "COFFEE TABLE": false, "COUCH": false}, "has_intervene": true, "type": "MainPage"}, "36": {"task": 2, "type": "MainPage", "dateString": "2019-04-18T17:37:58.857Z", "name": "ResultFinishedInternvention"}, "35": {"task": 2, "type": "MainPage", "dateString": "2019-04-18T17:37:28.309Z", "name": "ResultIntervention"}, "34": {"task": 2, "type": "MainPage", "dateString": "2019-04-18T17:37:23.381Z", "name": "HeadSuccessful"}, "33": {"task": 2, "type": "MainPage", "dateString": "2019-04-18T17:37:23.380Z", "name": "HeadFinishedIntervention"}, "32": {"task": 2, "name": "HeadMovedUD", "dateString": "2019-04-18T17:37:20.889Z", "heady": -29, "headx": -117, "type": "MainPage"}}